{
	"name": "1_ADE_source_copy_prop",
	"properties": {
		"linkedServiceName": {
			"referenceName": "LS_DataLake",
			"type": "LinkedServiceReference"
		},
		"annotations": [],
		"type": "DelimitedText",
		"typeProperties": {
			"location": {
				"type": "AzureBlobFSLocation",
				"fileName": "products.csv",
				"folderPath": "csv-files",
				"fileSystem": "source"
			},
			"columnDelimiter": ",",
			"escapeChar": "\\",
			"firstRowAsHeader": true,
			"quoteChar": "\""
		},
		"schema": []
	},
	"type": "Microsoft.DataFactory/factories/datasets"
}