{
	"name": "dest_copy_prop_3",
	"properties": {
		"linkedServiceName": {
			"referenceName": "LS_DataLake",
			"type": "LinkedServiceReference"
		},
		"parameters": {
			"p_filename_dest": {
				"type": "string"
			}
		},
		"annotations": [],
		"type": "DelimitedText",
		"typeProperties": {
			"location": {
				"type": "AzureBlobFSLocation",
				"fileName": {
					"value": "@dataset().p_filename_dest",
					"type": "Expression"
				},
				"folderPath": "csv-files",
				"fileSystem": "destination"
			},
			"columnDelimiter": ",",
			"escapeChar": "\\",
			"firstRowAsHeader": true,
			"quoteChar": "\""
		},
		"schema": []
	},
	"type": "Microsoft.DataFactory/factories/datasets"
}